{
    "compos": [
        {
            "column_max": 480,
            "row_min": 24,
            "row_max": 46,
            "class": "Compo",
            "id": 1,
            "height": 22,
            "column_min": 457,
            "width": 23
        },
        {
            "column_max": 45,
            "row_min": 25,
            "row_max": 30,
            "class": "Compo",
            "id": 2,
            "height": 5,
            "column_min": 21,
            "width": 24
        },
        {
            "column_max": 137,
            "row_min": 26,
            "row_max": 46,
            "class": "Compo",
            "id": 3,
            "height": 20,
            "column_min": 78,
            "width": 59
        },
        {
            "column_max": 46,
            "row_min": 33,
            "row_max": 43,
            "class": "Compo",
            "id": 4,
            "height": 10,
            "column_min": 21,
            "width": 25
        },
        {
            "column_max": 143,
            "row_min": 92,
            "row_max": 106,
            "class": "Compo",
            "id": 5,
            "height": 14,
            "column_min": 106,
            "width": 37
        },
        {
            "column_max": 413,
            "row_min": 92,
            "row_max": 106,
            "class": "Compo",
            "id": 6,
            "height": 14,
            "column_min": 336,
            "width": 77
        },
        {
            "column_max": 58,
            "row_min": 156,
            "row_max": 196,
            "class": "Compo",
            "id": 7,
            "height": 40,
            "column_min": 19,
            "width": 39
        },
        {
            "column_max": 124,
            "row_min": 161,
            "row_max": 176,
            "class": "Compo",
            "id": 8,
            "height": 15,
            "column_min": 72,
            "width": 52
        },
        {
            "column_max": 110,
            "row_min": 179,
            "row_max": 190,
            "class": "Compo",
            "id": 9,
            "height": 11,
            "column_min": 72,
            "width": 38
        },
        {
            "column_max": 137,
            "row_min": 180,
            "row_max": 190,
            "class": "Compo",
            "id": 10,
            "height": 10,
            "column_min": 112,
            "width": 25
        },
        {
            "column_max": 184,
            "row_min": 180,
            "row_max": 190,
            "class": "Compo",
            "id": 11,
            "height": 10,
            "column_min": 140,
            "width": 44
        },
        {
            "column_max": 208,
            "row_min": 182,
            "row_max": 193,
            "class": "Compo",
            "id": 12,
            "height": 11,
            "column_min": 187,
            "width": 21
        },
        {
            "column_max": 123,
            "row_min": 204,
            "row_max": 351,
            "class": "Compo",
            "id": 13,
            "height": 147,
            "column_min": 65,
            "width": 58
        },
        {
            "column_max": 226,
            "row_min": 217,
            "row_max": 234,
            "class": "Compo",
            "id": 14,
            "height": 17,
            "column_min": 189,
            "width": 37
        },
        {
            "column_max": 262,
            "row_min": 217,
            "row_max": 234,
            "class": "Compo",
            "id": 15,
            "height": 17,
            "column_min": 226,
            "width": 36
        },
        {
            "column_max": 292,
            "row_min": 217,
            "row_max": 234,
            "class": "Compo",
            "id": 16,
            "height": 17,
            "column_min": 275,
            "width": 17
        },
        {
            "column_max": 317,
            "row_min": 216,
            "row_max": 234,
            "class": "Compo",
            "id": 17,
            "height": 18,
            "column_min": 294,
            "width": 23
        },
        {
            "column_max": 371,
            "row_min": 217,
            "row_max": 235,
            "class": "Compo",
            "id": 18,
            "height": 18,
            "column_min": 323,
            "width": 48
        },
        {
            "column_max": 453,
            "row_min": 217,
            "row_max": 235,
            "class": "Compo",
            "id": 19,
            "height": 18,
            "column_min": 377,
            "width": 76
        },
        {
            "column_max": 209,
            "row_min": 239,
            "row_max": 261,
            "class": "Compo",
            "id": 20,
            "height": 22,
            "column_min": 189,
            "width": 20
        },
        {
            "column_max": 225,
            "row_min": 242,
            "row_max": 261,
            "class": "Compo",
            "id": 21,
            "height": 19,
            "column_min": 213,
            "width": 12
        },
        {
            "column_max": 254,
            "row_min": 241,
            "row_max": 261,
            "class": "Compo",
            "id": 22,
            "height": 20,
            "column_min": 230,
            "width": 24
        },
        {
            "column_max": 259,
            "row_min": 242,
            "row_max": 261,
            "class": "Compo",
            "id": 23,
            "height": 19,
            "column_min": 256,
            "width": 3
        },
        {
            "column_max": 307,
            "row_min": 241,
            "row_max": 264,
            "class": "Compo",
            "id": 24,
            "height": 23,
            "column_min": 261,
            "width": 46
        },
        {
            "column_max": 58,
            "row_min": 398,
            "row_max": 438,
            "class": "Compo",
            "id": 25,
            "height": 40,
            "column_min": 18,
            "width": 40
        },
        {
            "column_max": 104,
            "row_min": 403,
            "row_max": 416,
            "class": "Compo",
            "id": 26,
            "height": 13,
            "column_min": 71,
            "width": 33
        },
        {
            "column_max": 110,
            "row_min": 422,
            "row_max": 434,
            "class": "Compo",
            "id": 27,
            "height": 12,
            "column_min": 72,
            "width": 38
        },
        {
            "column_max": 137,
            "row_min": 422,
            "row_max": 432,
            "class": "Compo",
            "id": 28,
            "height": 10,
            "column_min": 113,
            "width": 24
        },
        {
            "column_max": 184,
            "row_min": 422,
            "row_max": 434,
            "class": "Compo",
            "id": 29,
            "height": 12,
            "column_min": 140,
            "width": 44
        },
        {
            "column_max": 208,
            "row_min": 424,
            "row_max": 435,
            "class": "Compo",
            "id": 30,
            "height": 11,
            "column_min": 187,
            "width": 21
        },
        {
            "column_max": 121,
            "row_min": 447,
            "row_max": 594,
            "class": "Compo",
            "id": 31,
            "height": 147,
            "column_min": 62,
            "width": 59
        },
        {
            "column_max": 222,
            "row_min": 459,
            "row_max": 478,
            "class": "Compo",
            "id": 32,
            "height": 19,
            "column_min": 188,
            "width": 34
        },
        {
            "column_max": 261,
            "row_min": 459,
            "row_max": 479,
            "class": "Compo",
            "id": 33,
            "height": 20,
            "column_min": 224,
            "width": 37
        },
        {
            "column_max": 316,
            "row_min": 459,
            "row_max": 478,
            "class": "Compo",
            "id": 34,
            "height": 19,
            "column_min": 266,
            "width": 50
        },
        {
            "column_max": 362,
            "row_min": 459,
            "row_max": 478,
            "class": "Compo",
            "id": 35,
            "height": 19,
            "column_min": 321,
            "width": 41
        },
        {
            "column_max": 398,
            "row_min": 458,
            "row_max": 478,
            "class": "Compo",
            "id": 36,
            "height": 20,
            "column_min": 367,
            "width": 31
        },
        {
            "column_max": 432,
            "row_min": 458,
            "row_max": 478,
            "class": "Compo",
            "id": 37,
            "height": 20,
            "column_min": 403,
            "width": 29
        },
        {
            "column_max": 445,
            "row_min": 463,
            "row_max": 477,
            "class": "Compo",
            "id": 38,
            "height": 14,
            "column_min": 433,
            "width": 12
        },
        {
            "column_max": 58,
            "row_min": 641,
            "row_max": 681,
            "class": "Compo",
            "id": 39,
            "height": 40,
            "column_min": 18,
            "width": 40
        },
        {
            "column_max": 106,
            "row_min": 645,
            "row_max": 659,
            "class": "Compo",
            "id": 40,
            "height": 14,
            "column_min": 72,
            "width": 34
        },
        {
            "column_max": 110,
            "row_min": 664,
            "row_max": 675,
            "class": "Compo",
            "id": 41,
            "height": 11,
            "column_min": 72,
            "width": 38
        },
        {
            "column_max": 138,
            "row_min": 665,
            "row_max": 675,
            "class": "Compo",
            "id": 42,
            "height": 10,
            "column_min": 112,
            "width": 26
        },
        {
            "column_max": 184,
            "row_min": 665,
            "row_max": 675,
            "class": "Compo",
            "id": 43,
            "height": 10,
            "column_min": 140,
            "width": 44
        },
        {
            "column_max": 208,
            "row_min": 667,
            "row_max": 678,
            "class": "Compo",
            "id": 44,
            "height": 11,
            "column_min": 187,
            "width": 21
        },
        {
            "column_max": 143,
            "row_min": 690,
            "row_max": 799,
            "class": "Compo",
            "id": 45,
            "height": 109,
            "column_min": 18,
            "width": 125
        },
        {
            "column_max": 197,
            "row_min": 702,
            "row_max": 719,
            "class": "Compo",
            "id": 46,
            "height": 17,
            "column_min": 189,
            "width": 8
        },
        {
            "column_max": 213,
            "row_min": 702,
            "row_max": 719,
            "class": "Compo",
            "id": 47,
            "height": 17,
            "column_min": 199,
            "width": 14
        },
        {
            "column_max": 284,
            "row_min": 701,
            "row_max": 719,
            "class": "Compo",
            "id": 48,
            "height": 18,
            "column_min": 219,
            "width": 65
        },
        {
            "column_max": 355,
            "row_min": 702,
            "row_max": 719,
            "class": "Compo",
            "id": 49,
            "height": 17,
            "column_min": 291,
            "width": 64
        },
        {
            "column_max": 375,
            "row_min": 702,
            "row_max": 719,
            "class": "Compo",
            "id": 50,
            "height": 17,
            "column_min": 361,
            "width": 14
        },
        {
            "column_max": 409,
            "row_min": 701,
            "row_max": 719,
            "class": "Compo",
            "id": 51,
            "height": 18,
            "column_min": 374,
            "width": 35
        },
        {
            "column_max": 462,
            "row_min": 702,
            "row_max": 724,
            "class": "Compo",
            "id": 52,
            "height": 22,
            "column_min": 414,
            "width": 48
        },
        {
            "column_max": 225,
            "row_min": 725,
            "row_max": 747,
            "class": "Compo",
            "id": 53,
            "height": 22,
            "column_min": 189,
            "width": 36
        },
        {
            "column_max": 254,
            "row_min": 726,
            "row_max": 745,
            "class": "Compo",
            "id": 54,
            "height": 19,
            "column_min": 230,
            "width": 24
        },
        {
            "column_max": 259,
            "row_min": 727,
            "row_max": 744,
            "class": "Compo",
            "id": 55,
            "height": 17,
            "column_min": 256,
            "width": 3
        },
        {
            "column_max": 307,
            "row_min": 726,
            "row_max": 749,
            "class": "Compo",
            "id": 56,
            "height": 23,
            "column_min": 261,
            "width": 46
        }
    ],
    "img_shape": [
        800,
        497,
        3
    ]
}