{
    "compos": [
        {
            "column_max": 481,
            "row_min": 10,
            "row_max": 49,
            "class": "Compo",
            "id": 1,
            "height": 39,
            "column_min": 418,
            "width": 63
        },
        {
            "column_max": 43,
            "row_min": 18,
            "row_max": 41,
            "class": "Compo",
            "id": 2,
            "height": 23,
            "column_min": 17,
            "width": 26
        },
        {
            "column_max": 140,
            "row_min": 73,
            "row_max": 91,
            "class": "Compo",
            "id": 3,
            "height": 18,
            "column_min": 96,
            "width": 44
        },
        {
            "column_max": 214,
            "row_min": 73,
            "row_max": 92,
            "class": "Compo",
            "id": 4,
            "height": 19,
            "column_min": 144,
            "width": 70
        },
        {
            "column_max": 264,
            "row_min": 73,
            "row_max": 94,
            "class": "Compo",
            "id": 5,
            "height": 21,
            "column_min": 217,
            "width": 47
        },
        {
            "column_max": 351,
            "row_min": 73,
            "row_max": 92,
            "class": "Compo",
            "id": 6,
            "height": 19,
            "column_min": 268,
            "width": 83
        },
        {
            "column_max": 396,
            "row_min": 77,
            "row_max": 96,
            "class": "Compo",
            "id": 7,
            "height": 19,
            "column_min": 355,
            "width": 41
        },
        {
            "column_max": 93,
            "row_min": 104,
            "row_max": 118,
            "class": "Compo",
            "id": 8,
            "height": 14,
            "column_min": 67,
            "width": 26
        },
        {
            "column_max": 152,
            "row_min": 102,
            "row_max": 118,
            "class": "Compo",
            "id": 9,
            "height": 16,
            "column_min": 96,
            "width": 56
        },
        {
            "column_max": 189,
            "row_min": 101,
            "row_max": 118,
            "class": "Compo",
            "id": 10,
            "height": 17,
            "column_min": 154,
            "width": 35
        },
        {
            "column_max": 233,
            "row_min": 102,
            "row_max": 118,
            "class": "Compo",
            "id": 11,
            "height": 16,
            "column_min": 192,
            "width": 41
        },
        {
            "column_max": 333,
            "row_min": 102,
            "row_max": 119,
            "class": "Compo",
            "id": 12,
            "height": 17,
            "column_min": 236,
            "width": 97
        },
        {
            "column_max": 350,
            "row_min": 104,
            "row_max": 118,
            "class": "Compo",
            "id": 13,
            "height": 14,
            "column_min": 336,
            "width": 14
        },
        {
            "column_max": 424,
            "row_min": 101,
            "row_max": 118,
            "class": "Compo",
            "id": 14,
            "height": 17,
            "column_min": 388,
            "width": 36
        },
        {
            "column_max": 386,
            "row_min": 107,
            "row_max": 123,
            "class": "Compo",
            "id": 15,
            "height": 16,
            "column_min": 353,
            "width": 33
        },
        {
            "column_max": 137,
            "row_min": 162,
            "row_max": 279,
            "class": "Compo",
            "id": 16,
            "height": 117,
            "column_min": 20,
            "width": 117
        },
        {
            "column_max": 305,
            "row_min": 161,
            "row_max": 280,
            "class": "Compo",
            "id": 17,
            "height": 119,
            "column_min": 187,
            "width": 118
        },
        {
            "column_max": 472,
            "row_min": 161,
            "row_max": 280,
            "class": "Compo",
            "id": 18,
            "height": 119,
            "column_min": 354,
            "width": 118
        },
        {
            "column_max": 102,
            "row_min": 300,
            "row_max": 317,
            "class": "Compo",
            "id": 19,
            "height": 17,
            "column_min": 57,
            "width": 45
        },
        {
            "column_max": 264,
            "row_min": 300,
            "row_max": 315,
            "class": "Compo",
            "id": 20,
            "height": 15,
            "column_min": 229,
            "width": 35
        },
        {
            "column_max": 384,
            "row_min": 300,
            "row_max": 314,
            "class": "Compo",
            "id": 21,
            "height": 14,
            "column_min": 360,
            "width": 24
        },
        {
            "column_max": 416,
            "row_min": 299,
            "row_max": 314,
            "class": "Compo",
            "id": 22,
            "height": 15,
            "column_min": 387,
            "width": 29
        },
        {
            "column_max": 467,
            "row_min": 300,
            "row_max": 314,
            "class": "Compo",
            "id": 23,
            "height": 14,
            "column_min": 418,
            "width": 49
        },
        {
            "column_max": 311,
            "row_min": 351,
            "row_max": 474,
            "class": "Compo",
            "id": 24,
            "height": 123,
            "column_min": 180,
            "width": 131
        },
        {
            "column_max": 479,
            "row_min": 353,
            "row_max": 482,
            "class": "Compo",
            "id": 25,
            "height": 129,
            "column_min": 348,
            "width": 131
        },
        {
            "column_max": 138,
            "row_min": 363,
            "row_max": 480,
            "class": "Compo",
            "id": 26,
            "height": 117,
            "column_min": 20,
            "width": 118
        },
        {
            "column_max": 90,
            "row_min": 489,
            "row_max": 504,
            "class": "Compo",
            "id": 27,
            "height": 15,
            "column_min": 55,
            "width": 35
        },
        {
            "column_max": 104,
            "row_min": 489,
            "row_max": 504,
            "class": "Compo",
            "id": 28,
            "height": 15,
            "column_min": 93,
            "width": 11
        },
        {
            "column_max": 434,
            "row_min": 490,
            "row_max": 509,
            "class": "Compo",
            "id": 29,
            "height": 19,
            "column_min": 391,
            "width": 43
        },
        {
            "column_max": 260,
            "row_min": 504,
            "row_max": 522,
            "class": "Compo",
            "id": 30,
            "height": 18,
            "column_min": 198,
            "width": 62
        },
        {
            "column_max": 295,
            "row_min": 504,
            "row_max": 522,
            "class": "Compo",
            "id": 31,
            "height": 18,
            "column_min": 265,
            "width": 30
        },
        {
            "column_max": 124,
            "row_min": 510,
            "row_max": 528,
            "class": "Compo",
            "id": 32,
            "height": 18,
            "column_min": 32,
            "width": 92
        },
        {
            "column_max": 471,
            "row_min": 516,
            "row_max": 535,
            "class": "Compo",
            "id": 33,
            "height": 19,
            "column_min": 359,
            "width": 112
        },
        {
            "column_max": 144,
            "row_min": 551,
            "row_max": 682,
            "class": "Compo",
            "id": 34,
            "height": 131,
            "column_min": 13,
            "width": 131
        },
        {
            "column_max": 305,
            "row_min": 562,
            "row_max": 681,
            "class": "Compo",
            "id": 35,
            "height": 119,
            "column_min": 187,
            "width": 118
        },
        {
            "column_max": 472,
            "row_min": 562,
            "row_max": 680,
            "class": "Compo",
            "id": 36,
            "height": 118,
            "column_min": 354,
            "width": 118
        },
        {
            "column_max": 270,
            "row_min": 698,
            "row_max": 717,
            "class": "Compo",
            "id": 37,
            "height": 19,
            "column_min": 222,
            "width": 48
        },
        {
            "column_max": 435,
            "row_min": 699,
            "row_max": 718,
            "class": "Compo",
            "id": 38,
            "height": 19,
            "column_min": 392,
            "width": 43
        },
        {
            "column_max": 105,
            "row_min": 705,
            "row_max": 725,
            "class": "Compo",
            "id": 39,
            "height": 20,
            "column_min": 53,
            "width": 52
        },
        {
            "column_max": 135,
            "row_min": 762,
            "row_max": 799,
            "class": "Compo",
            "id": 40,
            "height": 37,
            "column_min": 25,
            "width": 110
        },
        {
            "column_max": 303,
            "row_min": 763,
            "row_max": 799,
            "class": "Compo",
            "id": 41,
            "height": 36,
            "column_min": 192,
            "width": 111
        },
        {
            "column_max": 470,
            "row_min": 764,
            "row_max": 797,
            "class": "Compo",
            "id": 42,
            "height": 33,
            "column_min": 440,
            "width": 30
        },
        {
            "column_max": 413,
            "row_min": 787,
            "row_max": 799,
            "class": "Compo",
            "id": 43,
            "height": 12,
            "column_min": 383,
            "width": 30
        }
    ],
    "img_shape": [
        800,
        497,
        3
    ]
}